wagtailatomicadmin/__init__.py
wagtailatomicadmin/static/wagtailadmin/css/core.css
wagtailatomicadmin/static/wagtailadmin/css/userbar.css
wagtailatomicadmin/static/wagtailadmin/css/layouts/compare-revisions.css
wagtailatomicadmin/static/wagtailadmin/css/layouts/home.css
wagtailatomicadmin/static/wagtailadmin/css/layouts/login.css
wagtailatomicadmin/static/wagtailadmin/css/layouts/page-editor.css
wagtailatomicadmin/static/wagtailadmin/css/panels/rich-text.css
wagtailatomicadmin-0.2.5.dist-info/DESCRIPTION.rst
wagtailatomicadmin-0.2.5.dist-info/METADATA
wagtailatomicadmin-0.2.5.dist-info/RECORD
wagtailatomicadmin-0.2.5.dist-info/WHEEL
wagtailatomicadmin-0.2.5.dist-info/metadata.json
wagtailatomicadmin-0.2.5.dist-info/top_level.txt
